hml/__init__.py
hml/approaches/__init__.py
hml/approaches/cuts/__init__.py
hml/approaches/cuts/cut.py
hml/approaches/cuts/cut_and_count.py
hml/approaches/cuts/cut_layer.py
hml/approaches/networks/__init__.py
hml/approaches/networks/cnns/__init__.py
hml/approaches/networks/cnns/simple_cnn.py
hml/approaches/networks/gnns/__init__.py
hml/approaches/networks/gnns/simple_gnn.py
hml/approaches/networks/mlps/__init__.py
hml/approaches/networks/mlps/simple_mlp.py
hml/approaches/trees/__init__.py
hml/approaches/trees/gradient_boosted_decision_tree.py
hml/datasets/__init__.py
hml/datasets/demo_z_tagging.py
hml/datasets/graph_dataset.py
hml/datasets/image_dataset.py
hml/datasets/set_dataset.py
hml/generators/__init__.py
hml/generators/madgraph5.py
hml/metrics/__init__.py
hml/metrics/max_significance.py
hml/metrics/rejection_at_efficiency.py
hml/observables/__init__.py
hml/observables/angular_distance.py
hml/observables/charge.py
hml/observables/invariant_mass.py
hml/observables/kinematics.py
hml/observables/n_subjettiness.py
hml/observables/observable.py
hml/observables/size.py
hml/observables/tag.py
hml/operations/__init__.py
hml/operations/fastjet_ops.py
hml/operations/keras_ops.py
hml/operations/repr_ops.py
hml/operations/uproot_ops.py
hml/physics_objects/__init__.py
hml/physics_objects/collective.py
hml/physics_objects/multiple.py
hml/physics_objects/nested.py
hml/physics_objects/physics_object.py
hml/physics_objects/single.py
hml/representations/__init__.py
hml/representations/graph.py
hml/representations/image.py
hml/representations/set.py
hep_ml_lab-0.4.3.dist-info/LICENSE
hep_ml_lab-0.4.3.dist-info/METADATA
hep_ml_lab-0.4.3.dist-info/WHEEL
hep_ml_lab-0.4.3.dist-info/RECORD
