Metadata-Version: 2.1
Name: hep-ml-lab
Version: 0.4.3
Summary: An end-to-end framework used for research combining high-energy physics phenomenology with machine learning.
Home-page: https://github.com/Star9daisy/hep-ml-lab
License: MIT
Keywords: high energy physics,machine learning,framework
Author: Star9daisy
Author-email: star9daisy@outlook.com
Requires-Python: >=3.9,<3.12
Classifier: License :: OSI Approved :: MIT License
Classifier: Programming Language :: Python :: 3
Classifier: Programming Language :: Python :: 3.9
Classifier: Programming Language :: Python :: 3.10
Classifier: Programming Language :: Python :: 3.11
Requires-Dist: awkward (>=2.5.1,<3.0.0)
Requires-Dist: beautifulsoup4 (>=4.12.2,<5.0.0)
Requires-Dist: dill (>=0.3.7,<0.4.0)
Requires-Dist: fastjet (>=3.4.1.3,<4.0.0.0)
Requires-Dist: keras (>=3.0.0)
Requires-Dist: matplotlib (>=3.8.2,<4.0.0)
Requires-Dist: numba (>=0.59.0,<0.60.0)
Requires-Dist: numpy (>=1.22,<2.0)
Requires-Dist: pandas (==2.0.3)
Requires-Dist: pexpect (>=4.9.0,<5.0.0)
Requires-Dist: rich (>=13.4.2,<14.0.0)
Requires-Dist: scikit-learn (>=1.2.2,<2.0.0)
Requires-Dist: seaborn (>=0.13.2,<0.14.0)
Requires-Dist: vector (>=1.3.0,<2.0.0)
Project-URL: Documentation, https://star9daisy.github.io/hep-ml-lab/
